Metadata-Version: 2.1
Name: z3c.rest-publisher
Version: 0.9.2
Summary: This product has the base classes to implement a REST-Server using the concepts of Zope-traverser (IBrowserPublisher)
Home-page: http://svn.plone.org/svn/collective/
Author: Rodrigo Ristow
Author-email: rodrigo@maxttor.com
License: GPL
Keywords: REST Zope IBrowserPublisher
Platform: UNKNOWN
Classifier: Programming Language :: Python :: 2.7
